slugifile/__init__.py
slugifile/cli.py
slugifile/slugifile.py
slugifile-0.1.16.dist-info/DESCRIPTION.rst
slugifile-0.1.16.dist-info/METADATA
slugifile-0.1.16.dist-info/RECORD
slugifile-0.1.16.dist-info/WHEEL
slugifile-0.1.16.dist-info/entry_points.txt
slugifile-0.1.16.dist-info/metadata.json
slugifile-0.1.16.dist-info/top_level.txt
