Metadata-Version: 2.0
Name: slugifile
Version: 0.1.16
Summary: Renames the filenames within the specified directory to be Unix friendly.
Home-page: https://github.com/codehutlabs/slugifile
Author: Robert Kuzma
Author-email: robert@codehut.io
License: MIT license
Keywords: slugifile
Platform: UNKNOWN
Classifier: Development Status :: 3 - Alpha
Classifier: Intended Audience :: Developers
Classifier: License :: OSI Approved :: MIT License
Classifier: Natural Language :: English
Classifier: Programming Language :: Python :: 3
Classifier: Programming Language :: Python :: 3.4
Classifier: Programming Language :: Python :: 3.5
Classifier: Programming Language :: Python :: 3.6
Classifier: Programming Language :: Python :: 3.7
Requires-Dist: Click (>=6.0)
Requires-Dist: python-slugify (==1.2.6)
